liteapi/__init__.py
liteapi/sdk.py
liteapi_sdk-3.0.3.dist-info/METADATA
liteapi_sdk-3.0.3.dist-info/WHEEL
liteapi_sdk-3.0.3.dist-info/top_level.txt
liteapi_sdk-3.0.3.dist-info/RECORD
