Metadata-Version: 2.1
Name: liteapi-sdk
Version: 3.0.3
Summary: A Python SDK for interacting with the LiteApi travel platform
Classifier: Programming Language :: Python :: 3
Classifier: License :: OSI Approved :: MIT License
Classifier: Operating System :: OS Independent
Requires-Python: >=3.6
Requires-Dist: requests >=2.25.1
